config/__init__.py
config/constants.py
core/__init__.py
core/context.py
core/enums.py
core/interfaces.py
core/stats.py
core/types.py
etl_concurrent_framework-0.1.1.dist-info/licenses/LICENSE
generators/__init__.py
generators/accounting_data.py
generators/sales.py
orchestration/__init__.py
orchestration/orchestrator.py
orchestration/performance.py
processors/__init__.py
processors/extract.py
processors/load.py
processors/output.py
processors/transform.py
utils/__init__.py
utils/concurrency.py
utils/enhanced_logging.py
utils/file_lock_manager.py
utils/file_utils.py
utils/logging.py
utils/resource_manager.py
utils/traceback_logger.py
etl_concurrent_framework-0.1.1.dist-info/METADATA
etl_concurrent_framework-0.1.1.dist-info/WHEEL
etl_concurrent_framework-0.1.1.dist-info/top_level.txt
etl_concurrent_framework-0.1.1.dist-info/RECORD
