Metadata-Version: 2.4
Name: etl_concurrent_framework
Version: 0.1.1
Summary: 可擴展的ETL併發處理框架
Home-page: https://github.com/yourusername/etl-concurrent-framework
Author: himmel0549
Author-email: allenli0549@gmail.com
Classifier: Programming Language :: Python :: 3
Classifier: License :: OSI Approved :: MIT License
Classifier: Operating System :: OS Independent
Requires-Python: >=3.8
License-File: LICENSE
Requires-Dist: pandas
Requires-Dist: numpy
Requires-Dist: openpyxl
Requires-Dist: pyarrow
Requires-Dist: psutil
Requires-Dist: et_xmlfile
Requires-Dist: python-dateutil
Requires-Dist: pytz
Requires-Dist: tzdata
Requires-Dist: six
Dynamic: author
Dynamic: author-email
Dynamic: classifier
Dynamic: description
Dynamic: description-content-type
Dynamic: home-page
Dynamic: license-file
Dynamic: requires-dist
Dynamic: requires-python
Dynamic: summary
